scriptax_jupyter_kernel/__init__.py
scriptax_jupyter_kernel/__main__.py
scriptax_jupyter_kernel/install.py
scriptax_jupyter_kernel/kernel.py
scriptax_jupyter_kernel-0.1.3.dist-info/LICENSE
scriptax_jupyter_kernel-0.1.3.dist-info/METADATA
scriptax_jupyter_kernel-0.1.3.dist-info/WHEEL
scriptax_jupyter_kernel-0.1.3.dist-info/top_level.txt
scriptax_jupyter_kernel-0.1.3.dist-info/RECORD
